README.md
octodns_lexicon.py
setup.cfg
setup.py
octodns_lexicon.egg-info/PKG-INFO
octodns_lexicon.egg-info/SOURCES.txt
octodns_lexicon.egg-info/dependency_links.txt
octodns_lexicon.egg-info/requires.txt
octodns_lexicon.egg-info/top_level.txt