Metadata-Version: 2.1
Name: octodns-lexicon
Version: 0.1.dev3
Summary: Lexicon provider for OctoDNS
Home-page: http://github.com/doddo/octodns-lexiconprovider
Author: Petter Hassberg
Author-email: dr.doddo@gmail.com
License: MIT
Platform: UNKNOWN
Classifier: Intended Audience :: Developers
Classifier: Intended Audience :: System Administrators
Classifier: Topic :: Software Development :: Libraries :: Python Modules
Classifier: Topic :: Internet :: Name Service (DNS)
Classifier: Topic :: System :: Systems Administration
Classifier: Topic :: Utilities
Classifier: License :: OSI Approved :: MIT License
Classifier: Programming Language :: Python :: 2.7
Classifier: Programming Language :: Python :: 3
